DynamicDict/DynamicDict.py
DynamicDict/__init__.py
dynamicdict-0.2.1.dist-info/LICENSE
dynamicdict-0.2.1.dist-info/WHEEL
dynamicdict-0.2.1.dist-info/METADATA
dynamicdict-0.2.1.dist-info/RECORD
