Metadata-Version: 2.1
Name: DynamicDict
Version: 0.2.1
Summary: A dictionary wrapper that allows attribute access and mutation using both dot notation and dictionary-style indexing.
Author-email: Shane Plesner <gebnar@gmail.com>
Requires-Python: >=3.8, <4.0
Classifier: License :: OSI Approved :: MIT License
Classifier: Programming Language :: Python
Classifier: Programming Language :: Python :: 3
Classifier: Programming Language :: Python :: 3.8
Classifier: Programming Language :: Python :: 3.9
Classifier: Programming Language :: Python :: 3.10
Classifier: Programming Language :: Python :: 3.11
Project-URL: Home, https://github.com/gebnar/PythonDynamicDict
